pysc/__init__.py
pysc/sc_linux.py
pysc/sc_windows.py
pysc/svc.exe
pysc/win_scm_api.py
pysc/include/__init__.py
pysc/include/skeleton/guard.h
pysc/include/skeleton/service.h
pysc/include/skeleton/singleton.h
pysc/tests/__init__.py
pysc/tests/test_scm.py
pysc-0.1.1.dist-info/DESCRIPTION.rst
pysc-0.1.1.dist-info/METADATA
pysc-0.1.1.dist-info/RECORD
pysc-0.1.1.dist-info/WHEEL
pysc-0.1.1.dist-info/metadata.json
pysc-0.1.1.dist-info/top_level.txt
