Metadata-Version: 2.0
Name: pysc
Version: 0.1.1
Summary: Service Control Manager for Windows and Linux
Home-page: UNKNOWN
Author: Seliverstov Maksim
Author-email: Maksim.V.Seliverstov@yandex.ru
License: UNKNOWN
Keywords: windows service,linux demon,service,demon,runit
Platform: UNKNOWN
